fastentrypoints.py
fastentrypoints-0.11.dist-info/METADATA
fastentrypoints-0.11.dist-info/RECORD
fastentrypoints-0.11.dist-info/WHEEL
fastentrypoints-0.11.dist-info/entry_points.txt
fastentrypoints-0.11.dist-info/top_level.txt
