Metadata-Version: 2.1
Name: fastentrypoints
Version: 0.11
Summary: Makes entry_points specified in setup.py load more quickly
Home-page: https://github.com/ninjaaron/fast-entry_points
Author: Aaron Christianson
Author-email: ninjaaron@gmail.com
License: BSD
Platform: UNKNOWN
